[ {
  "id" : "AWbgkg9_NEXFMlzHLBEB",
  "text" : "That aneurysm is a disaster area.",
  "translations" : {
    "russian" : "Эта аневризма в опасной области."
  },
  "tokens" : [ {
    "token" : "that",
    "startOffset" : 0,
    "endOffset" : 4,
    "position" : 0
  }, {
    "token" : "aneurysm",
    "startOffset" : 5,
    "endOffset" : 13,
    "position" : 1
  }, {
    "token" : "is",
    "startOffset" : 14,
    "endOffset" : 16,
    "position" : 2
  }, {
    "token" : "a",
    "startOffset" : 17,
    "endOffset" : 18,
    "position" : 3
  }, {
    "token" : "aster",
    "startOffset" : 19,
    "endOffset" : 27,
    "position" : 4
  }, {
    "token" : "area",
    "startOffset" : 28,
    "endOffset" : 32,
    "position" : 5
  } ],
  "contentScore" : null
} ]