[ {
  "id" : "AWoDW-6bDTAu_IiLeB5X",
  "text" : "Approbation not required.",
  "translations" : {
    "russian" : "Одобрения не требуется."
  },
  "tokens" : [ {
    "token" : "approbation",
    "startOffset" : 0,
    "endOffset" : 11,
    "position" : 0
  }, {
    "token" : "approbate",
    "startOffset" : 0,
    "endOffset" : 11,
    "position" : 0
  }, {
    "token" : "not",
    "startOffset" : 12,
    "endOffset" : 15,
    "position" : 1
  }, {
    "token" : "quired",
    "startOffset" : 16,
    "endOffset" : 24,
    "position" : 2
  } ],
  "contentScore" : null
} ]