[ {
  "id" : "AWoFXi-yDTAu_IiLfZwo",
  "text" : "Note the victim's clavicle.",
  "translations" : {
    "russian" : "Ключица не принадлежит жертве."
  },
  "tokens" : [ {
    "token" : "note",
    "startOffset" : 0,
    "endOffset" : 4,
    "position" : 0
  }, {
    "token" : "the",
    "startOffset" : 5,
    "endOffset" : 8,
    "position" : 1
  }, {
    "token" : "victim",
    "startOffset" : 9,
    "endOffset" : 17,
    "position" : 2
  }, {
    "token" : "clavicle",
    "startOffset" : 18,
    "endOffset" : 26,
    "position" : 3
  } ],
  "contentScore" : null
}, {
  "id" : "AWoFXjDvDTAu_IiLfZwr",
  "text" : "A bullet fractured his clavicle.",
  "translations" : {
    "russian" : "Пуля раздробила ему ключицу."
  },
  "tokens" : [ {
    "token" : "a",
    "startOffset" : 0,
    "endOffset" : 1,
    "position" : 0
  }, {
    "token" : "bullet",
    "startOffset" : 2,
    "endOffset" : 8,
    "position" : 1
  }, {
    "token" : "fracture",
    "startOffset" : 9,
    "endOffset" : 18,
    "position" : 2
  }, {
    "token" : "his",
    "startOffset" : 19,
    "endOffset" : 22,
    "position" : 3
  }, {
    "token" : "clavicle",
    "startOffset" : 23,
    "endOffset" : 31,
    "position" : 4
  } ],
  "contentScore" : null
}, {
  "id" : "AWoFXjQ3DTAu_IiLfZw2",
  "text" : "Andrew's left clavicle and right tibia.",
  "translations" : {
    "russian" : "Левая ключица и правая большая берцовая кость."
  },
  "tokens" : [ {
    "token" : "andrew",
    "startOffset" : 0,
    "endOffset" : 8,
    "position" : 0
  }, {
    "token" : "left",
    "startOffset" : 9,
    "endOffset" : 13,
    "position" : 1
  }, {
    "token" : "clavicle",
    "startOffset" : 14,
    "endOffset" : 22,
    "position" : 2
  }, {
    "token" : "and",
    "startOffset" : 23,
    "endOffset" : 26,
    "position" : 3
  }, {
    "token" : "right",
    "startOffset" : 27,
    "endOffset" : 32,
    "position" : 4
  }, {
    "token" : "tibia",
    "startOffset" : 33,
    "endOffset" : 38,
    "position" : 5
  } ],
  "contentScore" : null
}, {
  "id" : "AWoFXjZLDTAu_IiLfZw9",
  "text" : "Bullet passed underneath his left clavicle.",
  "translations" : {
    "russian" : "Пуля прошла под левой ключицей."
  },
  "tokens" : [ {
    "token" : "bullet",
    "startOffset" : 0,
    "endOffset" : 6,
    "position" : 0
  }, {
    "token" : "pass",
    "startOffset" : 7,
    "endOffset" : 13,
    "position" : 1
  }, {
    "token" : "underneath",
    "startOffset" : 14,
    "endOffset" : 24,
    "position" : 2
  }, {
    "token" : "his",
    "startOffset" : 25,
    "endOffset" : 28,
    "position" : 3
  }, {
    "token" : "left",
    "startOffset" : 29,
    "endOffset" : 33,
    "position" : 4
  }, {
    "token" : "clavicle",
    "startOffset" : 34,
    "endOffset" : 42,
    "position" : 5
  } ],
  "contentScore" : null
}, {
  "id" : "AWoFXjGIDTAu_IiLfZwt",
  "text" : "Okay, walk it up the clavicle.",
  "translations" : {
    "russian" : "Так что ведем до ключицы."
  },
  "tokens" : [ {
    "token" : "okay",
    "startOffset" : 0,
    "endOffset" : 4,
    "position" : 0
  }, {
    "token" : "walk",
    "startOffset" : 6,
    "endOffset" : 10,
    "position" : 1
  }, {
    "token" : "it",
    "startOffset" : 11,
    "endOffset" : 13,
    "position" : 2
  }, {
    "token" : "up",
    "startOffset" : 14,
    "endOffset" : 16,
    "position" : 3
  }, {
    "token" : "the",
    "startOffset" : 17,
    "endOffset" : 20,
    "position" : 4
  }, {
    "token" : "clavicle",
    "startOffset" : 21,
    "endOffset" : 29,
    "position" : 5
  } ],
  "contentScore" : null
}, {
  "id" : "AWoFXjX3DTAu_IiLfZw8",
  "text" : "You should probably show some clavicle.",
  "translations" : {
    "russian" : "Ты, вероятно, должна показать часть ключицы."
  },
  "tokens" : [ {
    "token" : "you",
    "startOffset" : 0,
    "endOffset" : 3,
    "position" : 0
  }, {
    "token" : "should",
    "startOffset" : 4,
    "endOffset" : 10,
    "position" : 1
  }, {
    "token" : "probably",
    "startOffset" : 11,
    "endOffset" : 19,
    "position" : 2
  }, {
    "token" : "show",
    "startOffset" : 20,
    "endOffset" : 24,
    "position" : 3
  }, {
    "token" : "some",
    "startOffset" : 25,
    "endOffset" : 29,
    "position" : 4
  }, {
    "token" : "clavicle",
    "startOffset" : 30,
    "endOffset" : 38,
    "position" : 5
  } ],
  "contentScore" : null
}, {
  "id" : "AWoFXjNPDTAu_IiLfZwz",
  "text" : "The right clavicle has been trisected.",
  "translations" : {
    "russian" : "Правую ключицу рассекли на три части."
  },
  "tokens" : [ {
    "token" : "the",
    "startOffset" : 0,
    "endOffset" : 3,
    "position" : 0
  }, {
    "token" : "right",
    "startOffset" : 4,
    "endOffset" : 9,
    "position" : 1
  }, {
    "token" : "clavicle",
    "startOffset" : 10,
    "endOffset" : 18,
    "position" : 2
  }, {
    "token" : "has",
    "startOffset" : 19,
    "endOffset" : 22,
    "position" : 3
  }, {
    "token" : "been",
    "startOffset" : 23,
    "endOffset" : 27,
    "position" : 4
  }, {
    "token" : "trisect",
    "startOffset" : 28,
    "endOffset" : 37,
    "position" : 5
  } ],
  "contentScore" : null
} ]