[ {
  "id" : "AWbgcwxMNEXFMlzHK6Tq",
  "text" : "Got the cooperation juice ready?",
  "translations" : {
    "russian" : "Сок для сотрудничества готов?"
  },
  "tokens" : [ {
    "token" : "got",
    "startOffset" : 0,
    "endOffset" : 3,
    "position" : 0
  }, {
    "token" : "the",
    "startOffset" : 4,
    "endOffset" : 7,
    "position" : 1
  }, {
    "token" : "cooperation",
    "startOffset" : 8,
    "endOffset" : 19,
    "position" : 2
  }, {
    "token" : "cooperate",
    "startOffset" : 8,
    "endOffset" : 19,
    "position" : 2
  }, {
    "token" : "juice",
    "startOffset" : 20,
    "endOffset" : 25,
    "position" : 3
  }, {
    "token" : "ready",
    "startOffset" : 26,
    "endOffset" : 31,
    "position" : 4
  } ],
  "contentScore" : null
} ]