[ {
  "id" : "AWoEEZAZDTAu_IiLecmZ",
  "text" : "Sex outdoors.",
  "translations" : {
    "russian" : "Секс на улице."
  },
  "tokens" : [ {
    "token" : "sex",
    "startOffset" : 0,
    "endOffset" : 3,
    "position" : 0
  }, {
    "token" : "outdoor",
    "startOffset" : 4,
    "endOffset" : 12,
    "position" : 1
  } ],
  "contentScore" : null
}, {
  "id" : "AWoEEZC1DTAu_IiLecmb",
  "text" : "So, it's outdoors?",
  "translations" : {
    "russian" : "Ч ак это ж на улице?"
  },
  "tokens" : [ {
    "token" : "so",
    "startOffset" : 0,
    "endOffset" : 2,
    "position" : 0
  }, {
    "token" : "it",
    "startOffset" : 4,
    "endOffset" : 8,
    "position" : 1
  }, {
    "token" : "outdoor",
    "startOffset" : 9,
    "endOffset" : 17,
    "position" : 2
  } ],
  "contentScore" : null
}, {
  "id" : "AWoEEZQBDTAu_IiLecmm",
  "text" : "He loves being outdoors.",
  "translations" : {
    "russian" : "Он любит бывать на улице."
  },
  "tokens" : [ {
    "token" : "he",
    "startOffset" : 0,
    "endOffset" : 2,
    "position" : 0
  }, {
    "token" : "love",
    "startOffset" : 3,
    "endOffset" : 8,
    "position" : 1
  }, {
    "token" : "being",
    "startOffset" : 9,
    "endOffset" : 14,
    "position" : 2
  }, {
    "token" : "bee",
    "startOffset" : 9,
    "endOffset" : 14,
    "position" : 2
  }, {
    "token" : "outdoor",
    "startOffset" : 15,
    "endOffset" : 23,
    "position" : 3
  } ],
  "contentScore" : null
}, {
  "id" : "AWoEEZbADTAu_IiLecms",
  "text" : "At least it's outdoors.",
  "translations" : {
    "russian" : "По крайне мере, на улице."
  },
  "tokens" : [ {
    "token" : "at",
    "startOffset" : 0,
    "endOffset" : 2,
    "position" : 0
  }, {
    "token" : "least",
    "startOffset" : 3,
    "endOffset" : 8,
    "position" : 1
  }, {
    "token" : "it",
    "startOffset" : 9,
    "endOffset" : 13,
    "position" : 2
  }, {
    "token" : "outdoor",
    "startOffset" : 14,
    "endOffset" : 22,
    "position" : 3
  } ],
  "contentScore" : null
}, {
  "id" : "AWoEEY9tDTAu_IiLecmX",
  "text" : "Or you good outdoors too?",
  "translations" : {
    "russian" : "Или на улице тоже растешь?"
  },
  "tokens" : [ {
    "token" : "or",
    "startOffset" : 0,
    "endOffset" : 2,
    "position" : 0
  }, {
    "token" : "you",
    "startOffset" : 3,
    "endOffset" : 6,
    "position" : 1
  }, {
    "token" : "good",
    "startOffset" : 7,
    "endOffset" : 11,
    "position" : 2
  }, {
    "token" : "outdoor",
    "startOffset" : 12,
    "endOffset" : 20,
    "position" : 3
  }, {
    "token" : "too",
    "startOffset" : 21,
    "endOffset" : 24,
    "position" : 4
  } ],
  "contentScore" : null
}, {
  "id" : "AWoEEZBnDTAu_IiLecma",
  "text" : "Even in the outdoors, huh?",
  "translations" : {
    "russian" : "Даже на улице воняет, ух..."
  },
  "tokens" : [ {
    "token" : "even",
    "startOffset" : 0,
    "endOffset" : 4,
    "position" : 0
  }, {
    "token" : "ev",
    "startOffset" : 0,
    "endOffset" : 4,
    "position" : 0
  }, {
    "token" : "in",
    "startOffset" : 5,
    "endOffset" : 7,
    "position" : 1
  }, {
    "token" : "the",
    "startOffset" : 8,
    "endOffset" : 11,
    "position" : 2
  }, {
    "token" : "outdoor",
    "startOffset" : 12,
    "endOffset" : 20,
    "position" : 3
  }, {
    "token" : "huh",
    "startOffset" : 22,
    "endOffset" : 25,
    "position" : 4
  } ],
  "contentScore" : null
}, {
  "id" : "AWoEEZgIDTAu_IiLecmw",
  "text" : "I was performing outdoors today.",
  "translations" : {
    "russian" : "Давала сегодня представление на открытом воздухе."
  },
  "tokens" : [ {
    "token" : "i",
    "startOffset" : 0,
    "endOffset" : 1,
    "position" : 0
  }, {
    "token" : "was",
    "startOffset" : 2,
    "endOffset" : 5,
    "position" : 1
  }, {
    "token" : "perform",
    "startOffset" : 6,
    "endOffset" : 16,
    "position" : 2
  }, {
    "token" : "outdoor",
    "startOffset" : 17,
    "endOffset" : 25,
    "position" : 3
  }, {
    "token" : "today",
    "startOffset" : 26,
    "endOffset" : 31,
    "position" : 4
  } ],
  "contentScore" : null
}, {
  "id" : "AWoEEZe6DTAu_IiLecmv",
  "text" : "The great outdoors stimulates the appetite.",
  "translations" : {
    "russian" : "На открытом воздухе всегда хочется есть."
  },
  "tokens" : [ {
    "token" : "the",
    "startOffset" : 0,
    "endOffset" : 3,
    "position" : 0
  }, {
    "token" : "great",
    "startOffset" : 4,
    "endOffset" : 9,
    "position" : 1
  }, {
    "token" : "outdoor",
    "startOffset" : 10,
    "endOffset" : 18,
    "position" : 2
  }, {
    "token" : "stimulate",
    "startOffset" : 19,
    "endOffset" : 29,
    "position" : 3
  }, {
    "token" : "the",
    "startOffset" : 30,
    "endOffset" : 33,
    "position" : 4
  }, {
    "token" : "appetite",
    "startOffset" : 34,
    "endOffset" : 42,
    "position" : 5
  } ],
  "contentScore" : null
}, {
  "id" : "AWoFM4siDTAu_IiLfR27",
  "text" : "Outdoors magazine wants to interview you.",
  "translations" : {
    "russian" : "Журнал На природе хочет взять у вас интервью."
  },
  "tokens" : [ {
    "token" : "outdoor",
    "startOffset" : 0,
    "endOffset" : 8,
    "position" : 0
  }, {
    "token" : "magazine",
    "startOffset" : 9,
    "endOffset" : 17,
    "position" : 1
  }, {
    "token" : "want",
    "startOffset" : 18,
    "endOffset" : 23,
    "position" : 2
  }, {
    "token" : "to",
    "startOffset" : 24,
    "endOffset" : 26,
    "position" : 3
  }, {
    "token" : "interview",
    "startOffset" : 27,
    "endOffset" : 36,
    "position" : 4
  }, {
    "token" : "you",
    "startOffset" : 37,
    "endOffset" : 40,
    "position" : 5
  } ],
  "contentScore" : null
}, {
  "id" : "AWoEEZhHDTAu_IiLecmx",
  "text" : "Fresh air, sunshine, the great outdoors.",
  "translations" : {
    "russian" : "Свежий воздух, солнце светит, на открытом воздухе чудесно."
  },
  "tokens" : [ {
    "token" : "fresh",
    "startOffset" : 0,
    "endOffset" : 5,
    "position" : 0
  }, {
    "token" : "air",
    "startOffset" : 6,
    "endOffset" : 9,
    "position" : 1
  }, {
    "token" : "sunshine",
    "startOffset" : 11,
    "endOffset" : 19,
    "position" : 2
  }, {
    "token" : "the",
    "startOffset" : 21,
    "endOffset" : 24,
    "position" : 3
  }, {
    "token" : "great",
    "startOffset" : 25,
    "endOffset" : 30,
    "position" : 4
  }, {
    "token" : "outdoor",
    "startOffset" : 31,
    "endOffset" : 39,
    "position" : 5
  } ],
  "contentScore" : null
} ]