[ {
  "id" : "AWoDlc_ADTAu_IiLeKCf",
  "text" : "That's awfully polite.",
  "translations" : {
    "russian" : "Любезно с его стороны."
  },
  "tokens" : [ {
    "token" : "that",
    "startOffset" : 0,
    "endOffset" : 6,
    "position" : 0
  }, {
    "token" : "awful",
    "startOffset" : 7,
    "endOffset" : 14,
    "position" : 1
  }, {
    "token" : "polite",
    "startOffset" : 15,
    "endOffset" : 21,
    "position" : 2
  } ],
  "contentScore" : null
}, {
  "id" : "AWoDlcvSDTAu_IiLeKCY",
  "text" : "You're too polite.",
  "translations" : {
    "russian" : "О, вы слишком любезны."
  },
  "tokens" : [ {
    "token" : "you're",
    "startOffset" : 0,
    "endOffset" : 6,
    "position" : 0
  }, {
    "token" : "too",
    "startOffset" : 7,
    "endOffset" : 10,
    "position" : 1
  }, {
    "token" : "polite",
    "startOffset" : 11,
    "endOffset" : 17,
    "position" : 2
  } ],
  "contentScore" : null
}, {
  "id" : "AWoD7VN5DTAu_IiLeVpI",
  "text" : "Politeness costs nothing, Bobby.",
  "translations" : {
    "russian" : "Вежливость ничего не стоит, Бобби."
  },
  "tokens" : [ {
    "token" : "politeness",
    "startOffset" : 0,
    "endOffset" : 10,
    "position" : 0
  }, {
    "token" : "polite",
    "startOffset" : 0,
    "endOffset" : 10,
    "position" : 0
  }, {
    "token" : "cost",
    "startOffset" : 11,
    "endOffset" : 16,
    "position" : 1
  }, {
    "token" : "nothing",
    "startOffset" : 17,
    "endOffset" : 24,
    "position" : 2
  }, {
    "token" : "bobby",
    "startOffset" : 26,
    "endOffset" : 31,
    "position" : 3
  } ],
  "contentScore" : null
}, {
  "id" : "AWoD7VUADTAu_IiLeVpN",
  "text" : "The politeness of kings.",
  "translations" : {
    "russian" : "Вежливость королей."
  },
  "tokens" : [ {
    "token" : "the",
    "startOffset" : 0,
    "endOffset" : 3,
    "position" : 0
  }, {
    "token" : "politeness",
    "startOffset" : 4,
    "endOffset" : 14,
    "position" : 1
  }, {
    "token" : "polite",
    "startOffset" : 4,
    "endOffset" : 14,
    "position" : 1
  }, {
    "token" : "of",
    "startOffset" : 15,
    "endOffset" : 17,
    "position" : 2
  }, {
    "token" : "king",
    "startOffset" : 18,
    "endOffset" : 23,
    "position" : 3
  } ],
  "contentScore" : null
}, {
  "id" : "AWoElVMlDTAu_IiLe1E9",
  "text" : "Polite, considerate, well-mannered.",
  "translations" : {
    "russian" : "Вежливые, тактичные, воспитанные."
  },
  "tokens" : [ {
    "token" : "polite",
    "startOffset" : 0,
    "endOffset" : 6,
    "position" : 0
  }, {
    "token" : "considerate",
    "startOffset" : 8,
    "endOffset" : 19,
    "position" : 1
  }, {
    "token" : "well",
    "startOffset" : 21,
    "endOffset" : 25,
    "position" : 2
  }, {
    "token" : "mannered",
    "startOffset" : 26,
    "endOffset" : 34,
    "position" : 3
  }, {
    "token" : "manner",
    "startOffset" : 26,
    "endOffset" : 34,
    "position" : 3
  } ],
  "contentScore" : null
}, {
  "id" : "AWoDlc8uDTAu_IiLeKCe",
  "text" : "Now he is polite.",
  "translations" : {
    "russian" : "Но сейчас он любезен."
  },
  "tokens" : [ {
    "token" : "now",
    "startOffset" : 0,
    "endOffset" : 3,
    "position" : 0
  }, {
    "token" : "he",
    "startOffset" : 4,
    "endOffset" : 6,
    "position" : 1
  }, {
    "token" : "is",
    "startOffset" : 7,
    "endOffset" : 9,
    "position" : 2
  }, {
    "token" : "polite",
    "startOffset" : 10,
    "endOffset" : 16,
    "position" : 3
  } ],
  "contentScore" : null
}, {
  "id" : "AWoD7T35DTAu_IiLeVoM",
  "text" : "Now, explain... politely.",
  "translations" : {
    "russian" : "А теперь объясняй, но только вежливо."
  },
  "tokens" : [ {
    "token" : "now",
    "startOffset" : 0,
    "endOffset" : 3,
    "position" : 0
  }, {
    "token" : "explain",
    "startOffset" : 5,
    "endOffset" : 12,
    "position" : 1
  }, {
    "token" : "polite",
    "startOffset" : 16,
    "endOffset" : 24,
    "position" : 2
  } ],
  "contentScore" : null
}, {
  "id" : "AWoD7VWNDTAu_IiLeVpP",
  "text" : "And, yes, also politeness.",
  "translations" : {
    "russian" : "И да, из вежливости."
  },
  "tokens" : [ {
    "token" : "and",
    "startOffset" : 0,
    "endOffset" : 3,
    "position" : 0
  }, {
    "token" : "yes",
    "startOffset" : 5,
    "endOffset" : 8,
    "position" : 1
  }, {
    "token" : "also",
    "startOffset" : 10,
    "endOffset" : 14,
    "position" : 2
  }, {
    "token" : "politeness",
    "startOffset" : 15,
    "endOffset" : 25,
    "position" : 3
  }, {
    "token" : "polite",
    "startOffset" : 15,
    "endOffset" : 25,
    "position" : 3
  } ],
  "contentScore" : null
}, {
  "id" : "AWoEk5oCDTAu_IiLe0wo",
  "text" : "Politeness is a virtue.",
  "translations" : {
    "russian" : "Вежливость - это добродетель."
  },
  "tokens" : [ {
    "token" : "politeness",
    "startOffset" : 0,
    "endOffset" : 10,
    "position" : 0
  }, {
    "token" : "polite",
    "startOffset" : 0,
    "endOffset" : 10,
    "position" : 0
  }, {
    "token" : "is",
    "startOffset" : 11,
    "endOffset" : 13,
    "position" : 1
  }, {
    "token" : "a",
    "startOffset" : 14,
    "endOffset" : 15,
    "position" : 2
  }, {
    "token" : "virtue",
    "startOffset" : 16,
    "endOffset" : 22,
    "position" : 3
  } ],
  "contentScore" : null
}, {
  "id" : "AWoDlcIXDTAu_IiLeKCA",
  "text" : "She's nice, and polite.",
  "translations" : {
    "russian" : "Она хорошая и вежливая."
  },
  "tokens" : [ {
    "token" : "she",
    "startOffset" : 0,
    "endOffset" : 5,
    "position" : 0
  }, {
    "token" : "nice",
    "startOffset" : 6,
    "endOffset" : 10,
    "position" : 1
  }, {
    "token" : "and",
    "startOffset" : 12,
    "endOffset" : 15,
    "position" : 2
  }, {
    "token" : "polite",
    "startOffset" : 16,
    "endOffset" : 22,
    "position" : 3
  } ],
  "contentScore" : null
}, {
  "id" : "AWoDlcg9DTAu_IiLeKCN",
  "text" : "Yes, very polite.",
  "translations" : {
    "russian" : "Да, и очень вежлива."
  },
  "tokens" : [ {
    "token" : "yes",
    "startOffset" : 0,
    "endOffset" : 3,
    "position" : 0
  }, {
    "token" : "very",
    "startOffset" : 5,
    "endOffset" : 9,
    "position" : 1
  }, {
    "token" : "polite",
    "startOffset" : 10,
    "endOffset" : 16,
    "position" : 2
  } ],
  "contentScore" : null
}, {
  "id" : "AWoD7VRkDTAu_IiLeVpL",
  "text" : "I can't abide politeness.",
  "translations" : {
    "russian" : "Терпеть не могу вежливость."
  },
  "tokens" : [ {
    "token" : "i",
    "startOffset" : 0,
    "endOffset" : 1,
    "position" : 0
  }, {
    "token" : "can't",
    "startOffset" : 2,
    "endOffset" : 7,
    "position" : 1
  }, {
    "token" : "abide",
    "startOffset" : 8,
    "endOffset" : 13,
    "position" : 2
  }, {
    "token" : "politeness",
    "startOffset" : 14,
    "endOffset" : 24,
    "position" : 3
  }, {
    "token" : "polite",
    "startOffset" : 14,
    "endOffset" : 24,
    "position" : 3
  } ],
  "contentScore" : null
}, {
  "id" : "AWoETuDEDTAu_IiLeoA3",
  "text" : "I can't abide politeness.",
  "translations" : {
    "russian" : "Терпеть не могу вежливость."
  },
  "tokens" : [ {
    "token" : "i",
    "startOffset" : 0,
    "endOffset" : 1,
    "position" : 0
  }, {
    "token" : "can't",
    "startOffset" : 2,
    "endOffset" : 7,
    "position" : 1
  }, {
    "token" : "abide",
    "startOffset" : 8,
    "endOffset" : 13,
    "position" : 2
  }, {
    "token" : "politeness",
    "startOffset" : 14,
    "endOffset" : 24,
    "position" : 3
  }, {
    "token" : "polite",
    "startOffset" : 14,
    "endOffset" : 24,
    "position" : 3
  } ],
  "contentScore" : null
}, {
  "id" : "AWoEqJF_DTAu_IiLe4rr",
  "text" : "Politeness is a virtue.",
  "translations" : {
    "russian" : "Вежливость это добродетель."
  },
  "tokens" : [ {
    "token" : "politeness",
    "startOffset" : 0,
    "endOffset" : 10,
    "position" : 0
  }, {
    "token" : "polite",
    "startOffset" : 0,
    "endOffset" : 10,
    "position" : 0
  }, {
    "token" : "is",
    "startOffset" : 11,
    "endOffset" : 13,
    "position" : 1
  }, {
    "token" : "a",
    "startOffset" : 14,
    "endOffset" : 15,
    "position" : 2
  }, {
    "token" : "virtue",
    "startOffset" : 16,
    "endOffset" : 22,
    "position" : 3
  } ],
  "contentScore" : null
}, {
  "id" : "AWoDlcXiDTAu_IiLeKCH",
  "text" : "See, they're just being polite.",
  "translations" : {
    "russian" : "Они просто ведут себя вежливо."
  },
  "tokens" : [ {
    "token" : "see",
    "startOffset" : 0,
    "endOffset" : 3,
    "position" : 0
  }, {
    "token" : "they're",
    "startOffset" : 5,
    "endOffset" : 12,
    "position" : 1
  }, {
    "token" : "just",
    "startOffset" : 13,
    "endOffset" : 17,
    "position" : 2
  }, {
    "token" : "being",
    "startOffset" : 18,
    "endOffset" : 23,
    "position" : 3
  }, {
    "token" : "bee",
    "startOffset" : 18,
    "endOffset" : 23,
    "position" : 3
  }, {
    "token" : "polite",
    "startOffset" : 24,
    "endOffset" : 30,
    "position" : 4
  } ],
  "contentScore" : null
}, {
  "id" : "AWoDldZZDTAu_IiLeKCr",
  "text" : "There is no polite way.",
  "translations" : {
    "russian" : "Не существует изящного способа."
  },
  "tokens" : [ {
    "token" : "there",
    "startOffset" : 0,
    "endOffset" : 5,
    "position" : 0
  }, {
    "token" : "is",
    "startOffset" : 6,
    "endOffset" : 8,
    "position" : 1
  }, {
    "token" : "no",
    "startOffset" : 9,
    "endOffset" : 11,
    "position" : 2
  }, {
    "token" : "polite",
    "startOffset" : 12,
    "endOffset" : 18,
    "position" : 3
  }, {
    "token" : "way",
    "startOffset" : 19,
    "endOffset" : 22,
    "position" : 4
  } ],
  "contentScore" : null
} ]