[ {
  "id" : "AWoD6lDfDTAu_IiLeVOe",
  "text" : "Initiate female reaction sequence.",
  "translations" : {
    "russian" : "Начать тестовую проверку на женщин."
  },
  "tokens" : [ {
    "token" : "initiate",
    "startOffset" : 0,
    "endOffset" : 8,
    "position" : 0
  }, {
    "token" : "female",
    "startOffset" : 9,
    "endOffset" : 15,
    "position" : 1
  }, {
    "token" : "reaction",
    "startOffset" : 16,
    "endOffset" : 24,
    "position" : 2
  }, {
    "token" : "sequence",
    "startOffset" : 25,
    "endOffset" : 33,
    "position" : 3
  } ],
  "contentScore" : null
}, {
  "id" : "AWoDSlh5DTAu_IiLd_SU",
  "text" : "It's an allergic reaction!",
  "translations" : {
    "russian" : "У него аллергическая реакция!"
  },
  "tokens" : [ {
    "token" : "it",
    "startOffset" : 0,
    "endOffset" : 4,
    "position" : 0
  }, {
    "token" : "an",
    "startOffset" : 5,
    "endOffset" : 7,
    "position" : 1
  }, {
    "token" : "allergic",
    "startOffset" : 8,
    "endOffset" : 16,
    "position" : 2
  }, {
    "token" : "reaction",
    "startOffset" : 17,
    "endOffset" : 25,
    "position" : 3
  } ],
  "contentScore" : null
}, {
  "id" : "AWoFT0kBDTAu_IiLfXI9",
  "text" : "This reaction is catalyzed...",
  "translations" : {
    "russian" : "Катализатором реакции..."
  },
  "tokens" : [ {
    "token" : "this",
    "startOffset" : 0,
    "endOffset" : 4,
    "position" : 0
  }, {
    "token" : "reaction",
    "startOffset" : 5,
    "endOffset" : 13,
    "position" : 1
  }, {
    "token" : "is",
    "startOffset" : 14,
    "endOffset" : 16,
    "position" : 2
  }, {
    "token" : "catalyze",
    "startOffset" : 17,
    "endOffset" : 26,
    "position" : 3
  } ],
  "contentScore" : null
}, {
  "id" : "AWoESfuFDTAu_IiLenFc",
  "text" : "There was provocation then reaction.",
  "translations" : {
    "russian" : "Сначала была провокация, за ней последовала реакция."
  },
  "tokens" : [ {
    "token" : "there",
    "startOffset" : 0,
    "endOffset" : 5,
    "position" : 0
  }, {
    "token" : "was",
    "startOffset" : 6,
    "endOffset" : 9,
    "position" : 1
  }, {
    "token" : "vocation",
    "startOffset" : 10,
    "endOffset" : 21,
    "position" : 2
  }, {
    "token" : "th",
    "startOffset" : 22,
    "endOffset" : 26,
    "position" : 3
  }, {
    "token" : "reaction",
    "startOffset" : 27,
    "endOffset" : 35,
    "position" : 4
  } ],
  "contentScore" : null
}, {
  "id" : "AWoDjjOeDTAu_IiLeJAM",
  "text" : "That reaction time was abysmal.",
  "translations" : {
    "russian" : "Эта реакция была ужасной."
  },
  "tokens" : [ {
    "token" : "that",
    "startOffset" : 0,
    "endOffset" : 4,
    "position" : 0
  }, {
    "token" : "reaction",
    "startOffset" : 5,
    "endOffset" : 13,
    "position" : 1
  }, {
    "token" : "time",
    "startOffset" : 14,
    "endOffset" : 18,
    "position" : 2
  }, {
    "token" : "was",
    "startOffset" : 19,
    "endOffset" : 22,
    "position" : 3
  }, {
    "token" : "abysmal",
    "startOffset" : 23,
    "endOffset" : 30,
    "position" : 4
  } ],
  "contentScore" : null
}, {
  "id" : "AWoDSlrsDTAu_IiLd_Sa",
  "text" : "I had an allergic reaction.",
  "translations" : {
    "russian" : "У меня был аллергический шок!"
  },
  "tokens" : [ {
    "token" : "i",
    "startOffset" : 0,
    "endOffset" : 1,
    "position" : 0
  }, {
    "token" : "had",
    "startOffset" : 2,
    "endOffset" : 5,
    "position" : 1
  }, {
    "token" : "an",
    "startOffset" : 6,
    "endOffset" : 8,
    "position" : 2
  }, {
    "token" : "allergic",
    "startOffset" : 9,
    "endOffset" : 17,
    "position" : 3
  }, {
    "token" : "reaction",
    "startOffset" : 18,
    "endOffset" : 26,
    "position" : 4
  } ],
  "contentScore" : null
}, {
  "id" : "AWoDSl1fDTAu_IiLd_Si",
  "text" : "It's a severe allergic reaction.",
  "translations" : {
    "russian" : "Это сильная аллергическая реакция."
  },
  "tokens" : [ {
    "token" : "it",
    "startOffset" : 0,
    "endOffset" : 4,
    "position" : 0
  }, {
    "token" : "a",
    "startOffset" : 5,
    "endOffset" : 6,
    "position" : 1
  }, {
    "token" : "severe",
    "startOffset" : 7,
    "endOffset" : 13,
    "position" : 2
  }, {
    "token" : "allergic",
    "startOffset" : 14,
    "endOffset" : 22,
    "position" : 3
  }, {
    "token" : "reaction",
    "startOffset" : 23,
    "endOffset" : 31,
    "position" : 4
  } ],
  "contentScore" : null
}, {
  "id" : "AWoFWFihDTAu_IiLfYtX",
  "text" : "Intestines show no vital tissue reaction.",
  "translations" : {
    "russian" : "Ткани кишечника в полном порядке."
  },
  "tokens" : [ {
    "token" : "intestine",
    "startOffset" : 0,
    "endOffset" : 10,
    "position" : 0
  }, {
    "token" : "show",
    "startOffset" : 11,
    "endOffset" : 15,
    "position" : 1
  }, {
    "token" : "no",
    "startOffset" : 16,
    "endOffset" : 18,
    "position" : 2
  }, {
    "token" : "vital",
    "startOffset" : 19,
    "endOffset" : 24,
    "position" : 3
  }, {
    "token" : "tissue",
    "startOffset" : 25,
    "endOffset" : 31,
    "position" : 4
  }, {
    "token" : "reaction",
    "startOffset" : 32,
    "endOffset" : 40,
    "position" : 5
  } ],
  "contentScore" : null
}, {
  "id" : "AWoENWzjDTAu_IiLejUt",
  "text" : "An adverse reaction to the anesthetic.",
  "translations" : {
    "russian" : "Побочная реакция на анестезию."
  },
  "tokens" : [ {
    "token" : "an",
    "startOffset" : 0,
    "endOffset" : 2,
    "position" : 0
  }, {
    "token" : "adverse",
    "startOffset" : 3,
    "endOffset" : 10,
    "position" : 1
  }, {
    "token" : "reaction",
    "startOffset" : 11,
    "endOffset" : 19,
    "position" : 2
  }, {
    "token" : "to",
    "startOffset" : 20,
    "endOffset" : 22,
    "position" : 3
  }, {
    "token" : "the",
    "startOffset" : 23,
    "endOffset" : 26,
    "position" : 4
  }, {
    "token" : "anesthetic",
    "startOffset" : 27,
    "endOffset" : 37,
    "position" : 5
  } ],
  "contentScore" : null
}, {
  "id" : "AWoENWykDTAu_IiLejUs",
  "text" : "Must be having an adverse reaction.",
  "translations" : {
    "russian" : "Должно быть побочная реакция."
  },
  "tokens" : [ {
    "token" : "must",
    "startOffset" : 0,
    "endOffset" : 4,
    "position" : 0
  }, {
    "token" : "be",
    "startOffset" : 5,
    "endOffset" : 7,
    "position" : 1
  }, {
    "token" : "have",
    "startOffset" : 8,
    "endOffset" : 14,
    "position" : 2
  }, {
    "token" : "an",
    "startOffset" : 15,
    "endOffset" : 17,
    "position" : 3
  }, {
    "token" : "adverse",
    "startOffset" : 18,
    "endOffset" : 25,
    "position" : 4
  }, {
    "token" : "reaction",
    "startOffset" : 26,
    "endOffset" : 34,
    "position" : 5
  } ],
  "contentScore" : null
}, {
  "id" : "AWbgtv0ZNEXFMlzHLN4F",
  "text" : "Not to mention the people's reaction?",
  "translations" : {
    "russian" : "Что с реакцией населения?"
  },
  "tokens" : [ {
    "token" : "not",
    "startOffset" : 0,
    "endOffset" : 3,
    "position" : 0
  }, {
    "token" : "to",
    "startOffset" : 4,
    "endOffset" : 6,
    "position" : 1
  }, {
    "token" : "mention",
    "startOffset" : 7,
    "endOffset" : 14,
    "position" : 2
  }, {
    "token" : "the",
    "startOffset" : 15,
    "endOffset" : 18,
    "position" : 3
  }, {
    "token" : "people",
    "startOffset" : 19,
    "endOffset" : 27,
    "position" : 4
  }, {
    "token" : "reaction",
    "startOffset" : 28,
    "endOffset" : 36,
    "position" : 5
  } ],
  "contentScore" : null
}, {
  "id" : "AWoFB62VDTAu_IiLfJem",
  "text" : "Drain it and stop the reaction!",
  "translations" : {
    "russian" : "Опустошить его и остановить реакцию!"
  },
  "tokens" : [ {
    "token" : "drain",
    "startOffset" : 0,
    "endOffset" : 5,
    "position" : 0
  }, {
    "token" : "it",
    "startOffset" : 6,
    "endOffset" : 8,
    "position" : 1
  }, {
    "token" : "and",
    "startOffset" : 9,
    "endOffset" : 12,
    "position" : 2
  }, {
    "token" : "stop",
    "startOffset" : 13,
    "endOffset" : 17,
    "position" : 3
  }, {
    "token" : "the",
    "startOffset" : 18,
    "endOffset" : 21,
    "position" : 4
  }, {
    "token" : "reaction",
    "startOffset" : 22,
    "endOffset" : 30,
    "position" : 5
  } ],
  "contentScore" : null
}, {
  "id" : "AWbgba7YNEXFMlzHK5GY",
  "text" : "Not to mention the people's reaction?",
  "translations" : {
    "russian" : "Что с реакцией населения?"
  },
  "tokens" : [ {
    "token" : "not",
    "startOffset" : 0,
    "endOffset" : 3,
    "position" : 0
  }, {
    "token" : "to",
    "startOffset" : 4,
    "endOffset" : 6,
    "position" : 1
  }, {
    "token" : "mention",
    "startOffset" : 7,
    "endOffset" : 14,
    "position" : 2
  }, {
    "token" : "the",
    "startOffset" : 15,
    "endOffset" : 18,
    "position" : 3
  }, {
    "token" : "people",
    "startOffset" : 19,
    "endOffset" : 27,
    "position" : 4
  }, {
    "token" : "reaction",
    "startOffset" : 28,
    "endOffset" : 36,
    "position" : 5
  } ],
  "contentScore" : null
}, {
  "id" : "AWbgzTx6NEXFMlzHLWM0",
  "text" : "A reaction to Fancie's spicy shrimp.",
  "translations" : {
    "russian" : "Реакция на пряные креветки Фэнсис."
  },
  "tokens" : [ {
    "token" : "a",
    "startOffset" : 0,
    "endOffset" : 1,
    "position" : 0
  }, {
    "token" : "reaction",
    "startOffset" : 2,
    "endOffset" : 10,
    "position" : 1
  }, {
    "token" : "to",
    "startOffset" : 11,
    "endOffset" : 13,
    "position" : 2
  }, {
    "token" : "fancie",
    "startOffset" : 14,
    "endOffset" : 22,
    "position" : 3
  }, {
    "token" : "spicy",
    "startOffset" : 23,
    "endOffset" : 28,
    "position" : 4
  }, {
    "token" : "shrimp",
    "startOffset" : 29,
    "endOffset" : 35,
    "position" : 5
  } ],
  "contentScore" : null
}, {
  "id" : "AWoDSmAODTAu_IiLd_Sr",
  "text" : "Some sort of allergic reaction, maybe.",
  "translations" : {
    "russian" : "Какая-то аллергическая реакция, наверное."
  },
  "tokens" : [ {
    "token" : "some",
    "startOffset" : 0,
    "endOffset" : 4,
    "position" : 0
  }, {
    "token" : "sort",
    "startOffset" : 5,
    "endOffset" : 9,
    "position" : 1
  }, {
    "token" : "of",
    "startOffset" : 10,
    "endOffset" : 12,
    "position" : 2
  }, {
    "token" : "allergic",
    "startOffset" : 13,
    "endOffset" : 21,
    "position" : 3
  }, {
    "token" : "reaction",
    "startOffset" : 22,
    "endOffset" : 30,
    "position" : 4
  }, {
    "token" : "maybe",
    "startOffset" : 32,
    "endOffset" : 37,
    "position" : 5
  } ],
  "contentScore" : null
}, {
  "id" : "AWoDVGMyDTAu_IiLeA7O",
  "text" : "Is This A Reaction To Anesthesia?",
  "translations" : {
    "russian" : "Это реакция на анастезию?"
  },
  "tokens" : [ {
    "token" : "is",
    "startOffset" : 0,
    "endOffset" : 2,
    "position" : 0
  }, {
    "token" : "this",
    "startOffset" : 3,
    "endOffset" : 7,
    "position" : 1
  }, {
    "token" : "a",
    "startOffset" : 8,
    "endOffset" : 9,
    "position" : 2
  }, {
    "token" : "reaction",
    "startOffset" : 10,
    "endOffset" : 18,
    "position" : 3
  }, {
    "token" : "to",
    "startOffset" : 19,
    "endOffset" : 21,
    "position" : 4
  }, {
    "token" : "anesthesia",
    "startOffset" : 22,
    "endOffset" : 32,
    "position" : 5
  } ],
  "contentScore" : null
} ]