[ {
  "id" : "AWoDpkDuDTAu_IiLeMMT",
  "text" : "He snores like a bison.",
  "translations" : {
    "russian" : "Он храпит как бизон."
  },
  "tokens" : [ {
    "token" : "he",
    "startOffset" : 0,
    "endOffset" : 2,
    "position" : 0
  }, {
    "token" : "snore",
    "startOffset" : 3,
    "endOffset" : 9,
    "position" : 1
  }, {
    "token" : "like",
    "startOffset" : 10,
    "endOffset" : 14,
    "position" : 2
  }, {
    "token" : "a",
    "startOffset" : 15,
    "endOffset" : 16,
    "position" : 3
  }, {
    "token" : "bison",
    "startOffset" : 17,
    "endOffset" : 22,
    "position" : 4
  } ],
  "contentScore" : null
}, {
  "id" : "AWoFCwTQDTAu_IiLfKGK",
  "text" : "A-snoring in clown clothes.",
  "translations" : {
    "russian" : "Храпит в шутовском наряде!"
  },
  "tokens" : [ {
    "token" : "a",
    "startOffset" : 0,
    "endOffset" : 1,
    "position" : 0
  }, {
    "token" : "snore",
    "startOffset" : 2,
    "endOffset" : 9,
    "position" : 1
  }, {
    "token" : "in",
    "startOffset" : 10,
    "endOffset" : 12,
    "position" : 2
  }, {
    "token" : "clown",
    "startOffset" : 13,
    "endOffset" : 18,
    "position" : 3
  }, {
    "token" : "clothe",
    "startOffset" : 19,
    "endOffset" : 26,
    "position" : 4
  }, {
    "token" : "cloth",
    "startOffset" : 19,
    "endOffset" : 26,
    "position" : 4
  } ],
  "contentScore" : null
}, {
  "id" : "AWoDpcB1DTAu_IiLeMIC",
  "text" : "Gloria's snoring like a water buffalo.",
  "translations" : {
    "russian" : "Глория храпит как буйвол."
  },
  "tokens" : [ {
    "token" : "gloria",
    "startOffset" : 0,
    "endOffset" : 8,
    "position" : 0
  }, {
    "token" : "snore",
    "startOffset" : 9,
    "endOffset" : 16,
    "position" : 1
  }, {
    "token" : "like",
    "startOffset" : 17,
    "endOffset" : 21,
    "position" : 2
  }, {
    "token" : "a",
    "startOffset" : 22,
    "endOffset" : 23,
    "position" : 3
  }, {
    "token" : "water",
    "startOffset" : 24,
    "endOffset" : 29,
    "position" : 4
  }, {
    "token" : "buffalo",
    "startOffset" : 30,
    "endOffset" : 37,
    "position" : 5
  } ],
  "contentScore" : null
} ]