[ {
  "id" : "AWbgpVhPNEXFMlzHLIHS",
  "text" : "Mr. President, thirty seconds to airtime.",
  "translations" : {
    "russian" : "Господин президент, тридцать секунд до эфира."
  },
  "tokens" : [ {
    "token" : "mr",
    "startOffset" : 0,
    "endOffset" : 2,
    "position" : 0
  }, {
    "token" : "president",
    "startOffset" : 4,
    "endOffset" : 13,
    "position" : 1
  }, {
    "token" : "thirty",
    "startOffset" : 15,
    "endOffset" : 21,
    "position" : 2
  }, {
    "token" : "second",
    "startOffset" : 22,
    "endOffset" : 29,
    "position" : 3
  }, {
    "token" : "to",
    "startOffset" : 30,
    "endOffset" : 32,
    "position" : 4
  }, {
    "token" : "airtime",
    "startOffset" : 33,
    "endOffset" : 40,
    "position" : 5
  } ],
  "contentScore" : null
} ]