[ {
  "id" : "AWbgnX3rNEXFMlzHLFVu",
  "text" : "Stuff it, Tommy.",
  "translations" : {
    "russian" : "Что за чепуха, Томми."
  },
  "tokens" : [ {
    "token" : "stuff",
    "startOffset" : 0,
    "endOffset" : 5,
    "position" : 0
  }, {
    "token" : "it",
    "startOffset" : 6,
    "endOffset" : 8,
    "position" : 1
  }, {
    "token" : "tommy",
    "startOffset" : 10,
    "endOffset" : 15,
    "position" : 2
  } ],
  "contentScore" : null
}, {
  "id" : "AWbgh429NEXFMlzHK-uw",
  "text" : "Tommy, I'm a big girl.",
  "translations" : {
    "russian" : "Томми, я взрослая девочка."
  },
  "tokens" : [ {
    "token" : "tommy",
    "startOffset" : 0,
    "endOffset" : 5,
    "position" : 0
  }, {
    "token" : "i'm",
    "startOffset" : 7,
    "endOffset" : 10,
    "position" : 1
  }, {
    "token" : "a",
    "startOffset" : 11,
    "endOffset" : 12,
    "position" : 2
  }, {
    "token" : "big",
    "startOffset" : 13,
    "endOffset" : 16,
    "position" : 3
  }, {
    "token" : "girl",
    "startOffset" : 17,
    "endOffset" : 21,
    "position" : 4
  } ],
  "contentScore" : null
}, {
  "id" : "AWbgzR2TNEXFMlzHLWI9",
  "text" : "Tommy, we need more mild!",
  "translations" : {
    "russian" : "Томми, мы должны быть более мягкими."
  },
  "tokens" : [ {
    "token" : "tommy",
    "startOffset" : 0,
    "endOffset" : 5,
    "position" : 0
  }, {
    "token" : "we",
    "startOffset" : 7,
    "endOffset" : 9,
    "position" : 1
  }, {
    "token" : "need",
    "startOffset" : 10,
    "endOffset" : 14,
    "position" : 2
  }, {
    "token" : "more",
    "startOffset" : 15,
    "endOffset" : 19,
    "position" : 3
  }, {
    "token" : "mild",
    "startOffset" : 20,
    "endOffset" : 24,
    "position" : 4
  } ],
  "contentScore" : null
}, {
  "id" : "AWbgzOHZNEXFMlzHLWBF",
  "text" : "Tommy, the vegetables were delicious.",
  "translations" : {
    "russian" : "Томми, овощи были очень вкусными."
  },
  "tokens" : [ {
    "token" : "tommy",
    "startOffset" : 0,
    "endOffset" : 5,
    "position" : 0
  }, {
    "token" : "the",
    "startOffset" : 7,
    "endOffset" : 10,
    "position" : 1
  }, {
    "token" : "vegetable",
    "startOffset" : 11,
    "endOffset" : 21,
    "position" : 2
  }, {
    "token" : "were",
    "startOffset" : 22,
    "endOffset" : 26,
    "position" : 3
  }, {
    "token" : "delicious",
    "startOffset" : 27,
    "endOffset" : 36,
    "position" : 4
  } ],
  "contentScore" : null
}, {
  "id" : "AWbgjC9HNEXFMlzHK_sL",
  "text" : "All right, well, Tommy feels great.",
  "translations" : {
    "russian" : "Ладно, что ж, Томми чувствует себя отлично."
  },
  "tokens" : [ {
    "token" : "all",
    "startOffset" : 0,
    "endOffset" : 3,
    "position" : 0
  }, {
    "token" : "right",
    "startOffset" : 4,
    "endOffset" : 9,
    "position" : 1
  }, {
    "token" : "well",
    "startOffset" : 11,
    "endOffset" : 15,
    "position" : 2
  }, {
    "token" : "tommy",
    "startOffset" : 17,
    "endOffset" : 22,
    "position" : 3
  }, {
    "token" : "feel",
    "startOffset" : 23,
    "endOffset" : 28,
    "position" : 4
  }, {
    "token" : "great",
    "startOffset" : 29,
    "endOffset" : 34,
    "position" : 5
  } ],
  "contentScore" : null
}, {
  "id" : "AWbgyjKuNEXFMlzHLU9S",
  "text" : "They were transporting Tommy Littlestone's body.",
  "translations" : {
    "russian" : "Они перевозили тело Томми Литтлстоуна."
  },
  "tokens" : [ {
    "token" : "they",
    "startOffset" : 0,
    "endOffset" : 4,
    "position" : 0
  }, {
    "token" : "were",
    "startOffset" : 5,
    "endOffset" : 9,
    "position" : 1
  }, {
    "token" : "transport",
    "startOffset" : 10,
    "endOffset" : 22,
    "position" : 2
  }, {
    "token" : "tommy",
    "startOffset" : 23,
    "endOffset" : 28,
    "position" : 3
  }, {
    "token" : "littlestone's",
    "startOffset" : 29,
    "endOffset" : 42,
    "position" : 4
  }, {
    "token" : "body",
    "startOffset" : 43,
    "endOffset" : 47,
    "position" : 5
  } ],
  "contentScore" : null
}, {
  "id" : "AWbgl8ZMNEXFMlzHLDC5",
  "text" : "And, Tommy, do me a favor.",
  "translations" : {
    "russian" : "И, Томми, окажи мне услугу."
  },
  "tokens" : [ {
    "token" : "and",
    "startOffset" : 0,
    "endOffset" : 3,
    "position" : 0
  }, {
    "token" : "tommy",
    "startOffset" : 5,
    "endOffset" : 10,
    "position" : 1
  }, {
    "token" : "do",
    "startOffset" : 12,
    "endOffset" : 14,
    "position" : 2
  }, {
    "token" : "me",
    "startOffset" : 15,
    "endOffset" : 17,
    "position" : 3
  }, {
    "token" : "a",
    "startOffset" : 18,
    "endOffset" : 19,
    "position" : 4
  }, {
    "token" : "favor",
    "startOffset" : 20,
    "endOffset" : 25,
    "position" : 5
  } ],
  "contentScore" : null
}, {
  "id" : "AWbgzJbpNEXFMlzHLV3V",
  "text" : "Tommy, stop!",
  "translations" : {
    "russian" : "Томми, стойте!"
  },
  "tokens" : [ {
    "token" : "tommy",
    "startOffset" : 0,
    "endOffset" : 5,
    "position" : 0
  }, {
    "token" : "stop",
    "startOffset" : 7,
    "endOffset" : 11,
    "position" : 1
  } ],
  "contentScore" : "POOR"
} ]